pygp_particle_filter/__init__.py
pygp_particle_filter/observation.py
pygp_particle_filter/particle.py
pygp_particle_filter/particle_filter.py
pygp_particle_filter/tools.py
pygp_particle_filter-0.1.7.dist-info/METADATA
pygp_particle_filter-0.1.7.dist-info/WHEEL
pygp_particle_filter-0.1.7.dist-info/top_level.txt
pygp_particle_filter-0.1.7.dist-info/RECORD
